feast_azure_provider/__init__.py
feast_azure_provider/azure_provider.py
feast_azure_provider/mssqlserver.py
feast_azure_provider/mssqlserver_source.py
feast_azure_provider/registry_store.py
cbtham_feast_az_provider-0.2.302.dist-info/METADATA
cbtham_feast_az_provider-0.2.302.dist-info/WHEEL
cbtham_feast_az_provider-0.2.302.dist-info/top_level.txt
cbtham_feast_az_provider-0.2.302.dist-info/RECORD
