Metadata-Version: 2.1
Name: cbtham-feast-az-provider
Version: 0.2.302
Summary: A Feast Azure Provider
Home-page: UNKNOWN
Author: cbtham
License: MIT
Platform: UNKNOWN
Classifier: License :: OSI Approved :: MIT License
Classifier: Programming Language :: Python
Classifier: Programming Language :: Python :: 3
Classifier: Programming Language :: Python :: 3.7
Requires-Python: >=3.7.0
Requires-Dist: SQLAlchemy (>=1.4.19)
Requires-Dist: azure-identity (>=1.6.1)
Requires-Dist: azure-storage-blob (>=0.37.0)
Requires-Dist: dill (==0.3.4)
Requires-Dist: feast[redis] (==0.18.1)
Requires-Dist: pyodbc (>=4.0.30)
Provides-Extra: dev
Requires-Dist: assertpy ; extra == 'dev'
Requires-Dist: mypy ; extra == 'dev'
Requires-Dist: pytest ; extra == 'dev'
Provides-Extra: snowflake
Requires-Dist: snowflake-connector-python[pandas] (>=2.7.3) ; extra == 'snowflake'
